pkscreener-0.46.20260108.816.data/purelib/pkscreener/Disclaimer.txt
pkscreener-0.46.20260108.816.data/purelib/pkscreener/LICENSE-Others.txt
pkscreener-0.46.20260108.816.data/purelib/pkscreener/LICENSE.txt
pkscreener-0.46.20260108.816.data/purelib/pkscreener/LogoWM.txt
pkscreener-0.46.20260108.816.data/purelib/pkscreener/MainApplication.py
pkscreener-0.46.20260108.816.data/purelib/pkscreener/README.txt
pkscreener-0.46.20260108.816.data/purelib/pkscreener/__init__.py
pkscreener-0.46.20260108.816.data/purelib/pkscreener/courbd.ttf
pkscreener-0.46.20260108.816.data/purelib/pkscreener/globals.py
pkscreener-0.46.20260108.816.data/purelib/pkscreener/pkscreener.ini
pkscreener-0.46.20260108.816.data/purelib/pkscreener/pkscreenerbot.py
pkscreener-0.46.20260108.816.data/purelib/pkscreener/pkscreenercli.py
pkscreener-0.46.20260108.816.data/purelib/pkscreener/requirements.txt
pkscreener-0.46.20260108.816.data/purelib/pkscreener/classes/ArtTexts.py
pkscreener-0.46.20260108.816.data/purelib/pkscreener/classes/AssetsManager.py
pkscreener-0.46.20260108.816.data/purelib/pkscreener/classes/Backtest.py
pkscreener-0.46.20260108.816.data/purelib/pkscreener/classes/BacktestHandler.py
pkscreener-0.46.20260108.816.data/purelib/pkscreener/classes/BacktestUtils.py
pkscreener-0.46.20260108.816.data/purelib/pkscreener/classes/Barometer.py
pkscreener-0.46.20260108.816.data/purelib/pkscreener/classes/CandlePatterns.py
pkscreener-0.46.20260108.816.data/purelib/pkscreener/classes/Changelog.py
pkscreener-0.46.20260108.816.data/purelib/pkscreener/classes/ConfigManager.py
pkscreener-0.46.20260108.816.data/purelib/pkscreener/classes/ConsoleMenuUtility.py
pkscreener-0.46.20260108.816.data/purelib/pkscreener/classes/ConsoleUtility.py
pkscreener-0.46.20260108.816.data/purelib/pkscreener/classes/CoreFunctions.py
pkscreener-0.46.20260108.816.data/purelib/pkscreener/classes/DataLoader.py
pkscreener-0.46.20260108.816.data/purelib/pkscreener/classes/ExecuteOptionHandlers.py
pkscreener-0.46.20260108.816.dist-info/licenses/LICENSE
pkscreener-0.46.20260108.816.dist-info/METADATA
pkscreener-0.46.20260108.816.dist-info/WHEEL
pkscreener-0.46.20260108.816.dist-info/entry_points.txt
pkscreener-0.46.20260108.816.dist-info/top_level.txt
pkscreener-0.46.20260108.816.dist-info/RECORD
