Metadata-Version: 2.4
Name: pkscreener
Version: 0.46.20260108.816
Summary: A Python-based stock screener for NSE, India with alerts to Telegram Channel (pkscreener)
Home-page: https://github.com/pkjmesra/pkscreener
Download-URL: https://github.com/pkjmesra/pkscreener/archive/v0.46.20260108.816.zip
Author: pkjmesra
Author-email: pkjmesra@gmail.com
License: OSI Approved (MIT)
Keywords: NSE,Technical Indicators,Scanning,Stock Scanners
Classifier: License :: OSI Approved :: MIT License
Classifier: Operating System :: Microsoft :: Windows
Classifier: Operating System :: MacOS
Classifier: Operating System :: POSIX :: Linux
Classifier: Programming Language :: Python :: 3
Classifier: Programming Language :: Python :: 3.12
License-File: LICENSE
Dynamic: author
Dynamic: author-email
Dynamic: classifier
Dynamic: description
Dynamic: description-content-type
Dynamic: download-url
Dynamic: home-page
Dynamic: keywords
Dynamic: license
Dynamic: license-file
Dynamic: summary
